[
  {
    "title": "[글로벌 마켓 리포트 6월 25일]",
    "url": "https://www.newspim.com/news/view/20260625000190",
    "snippet": "[서울=뉴스핌] 최원진 기자= 24일(현지시간) 미국 뉴욕증시 주요 지수는 혼조세로 마감했다.이날 다우존스30산업평균지수는 전장보다 182.06포인트(0.35%) 오른 5만 1,848.90에 마감했다.반면 대형주 위주의 스탠더드앤드푸어스(...",
    "date": "1 day ago",
    "search_engine": "brave",
    "source": "search_운송지연_항만적체",
    "search_keyword": "글로벌 해운 지연",
    "theme": "운송지연_항만적체",
    "crawled_at": "2026-06-26T09:10:06.372184"
  },
  {
    "title": "동해시, 5년 새 3700명 줄어든 동해시…'글로벌 해양도시'로 도약할까",
    "url": "https://newspim.com/news/view/20260625000792",
    "snippet": "[동해=뉴스핌] 이형섭 기자 = 저출생과 청년·중년층 이탈이 겹치며 강원 동해시 인구가 5년 사이 4% 넘게 줄어든 것으로 나타났다.인구 구조는 '청년·중년 감소, 고령층 증가'로 빠르게 재편되는 가운데 이정학 동해시장 ...",
    "date": "19 hours ago",
    "search_engine": "brave",
    "source": "search_운송지연_항만적체",
    "search_keyword": "글로벌 해운 지연",
    "theme": "운송지연_항만적체",
    "crawled_at": "2026-06-26T09:10:06.372193"
  },
  {
    "title": "선박 호르무즈 탈출 시작됐지만…운임은 요지부동 \"3분기 지나야 안정\" - 파이낸셜뉴스",
    "url": "https://fnnews.com/news/202606260531107942",
    "snippet": "실제 글로벌 해운시장에서는 여전히 위험 해역 보험료와 선박 대기 비용, 운항 지연에 따른 스케줄 차질이 운임에 반영되고 있다.",
    "date": "4 hours ago",
    "search_engine": "brave",
    "source": "search_운송지연_항만적체",
    "search_keyword": "글로벌 해운 지연",
    "theme": "운송지연_항만적체",
    "crawled_at": "2026-06-26T09:10:06.372195"
  },
  {
    "title": "선박 호르무즈 탈출 시작됐지만…운임은 요지부동 \"3분기 지나야 안정\" - 파이낸셜뉴스",
    "url": "https://fnnews.com/news/202606260531107942",
    "snippet": "[서울=뉴시스] 미국과 이란의 종전 잠정 합의 이후 호르무즈 해협에 묶였던 선박들이 순차적으로 빠져나오고 있지만 가파르게 오른 해상운임은 단기간에 안정되기는 어려울 전망이다. 선박 통항 재개로 화물·선원 안전 우려는 ...",
    "date": "4 hours ago",
    "search_engine": "brave",
    "source": "search_운송지연_항만적체",
    "search_keyword": "항만 적체 컨테이너",
    "theme": "운송지연_항만적체",
    "crawled_at": "2026-06-26T09:10:06.699044"
  },
  {
    "title": "스페이스X에 알고보니 한국 부품이…사천에 있는 알짜기업 어디? - 머니투데이",
    "url": "https://mt.co.kr/tech/2026/06/25/2026062511063330956",
    "snippet": "\"한국 상장사 중 유일하게 스페이스X와 블루오리진 발사체에 부품을 공급하고 있습니다. \" 정재한 켄코아에어로 부사장(COO)은 24일 경남 사천 켄코아에어로스페이스 본사에서 우주항공청 기자단을 만나 이같이 말했다.",
    "date": "20 hours ago",
    "search_engine": "brave",
    "source": "search_운송지연_항만적체",
    "search_keyword": "항만 적체 컨테이너",
    "theme": "운송지연_항만적체",
    "crawled_at": "2026-06-26T09:10:06.699054"
  },
  {
    "title": "이란, 美에 \"모순된 발언 그만\" 경고...29~30일 협상 재개할 듯 - 파이낸셜뉴스",
    "url": "https://fnnews.com/news/202606250838269713",
    "snippet": "미국과 종전 협상을 벌이고 있는 이란 정부가 미국을 향해 양해각서와 \"모순된 발언\"으로 불신을 키우지 말라고 촉구했다.앞서 미국과 이란은 지난 21~22일 스위스에서 양해각서 체결 이후 첫 종전 실무협상을 벌였고 양측 ...",
    "date": "1 day ago",
    "search_engine": "brave",
    "source": "search_운송지연_항만적체",
    "search_keyword": "항만 적체 컨테이너",
    "theme": "운송지연_항만적체",
    "crawled_at": "2026-06-26T09:10:06.699056"
  },
  {
    "title": "UK DBT creates Supply Chain Centre to battle logistics uncertainty | Logistics Manager",
    "url": "https://logisticsmanager.com/uk-dbt-creates-supply-chain-centre-to-battle-logistics-uncertainty",
    "snippet": "The UK Department for Business and Trade has laid out a Supply Chain Centre mission statement and action plan to support British logistics.",
    "date": "15 hours ago",
    "search_engine": "brave",
    "source": "search_운송지연_항만적체",
    "search_keyword": "supply chain disruption logistics",
    "theme": "운송지연_항만적체",
    "crawled_at": "2026-06-26T09:10:07.067803"
  },
  {
    "title": "How autonomous systems are reshaping warehouse operations | TechRadar",
    "url": "https://techradar.com/pro/how-autonomous-systems-are-reshaping-warehouse-operations",
    "snippet": "Autonomy is becoming a foundational capability for modern logistics operations. The greatest value does not come from robotics alone, but from the ability to combine automation, AI and real-time operational intelligence into a single connected system. Warehouses that can continuously monitor inventory, identify inefficiencies and respond dynamically to changing conditions will be better positioned to manage disruption and scale sustainably. As supply chains ...",
    "date": "10 hours ago",
    "search_engine": "brave",
    "source": "search_운송지연_항만적체",
    "search_keyword": "supply chain disruption logistics",
    "theme": "운송지연_항만적체",
    "crawled_at": "2026-06-26T09:10:07.067815"
  },
  {
    "title": "Turning supply chain volatility into regional advantage | Arab News",
    "url": "https://arabnews.com/node/2648593",
    "snippet": "Supply chain resilience depends not only on companies but also on infrastructure, policy coordination, and institutional readiness. Continued disruption in the Red Sea and vessels avoiding the Suez Canal have underscored how tightly linked logistics networks, ports, customs authorities, and ...",
    "date": "5 hours ago",
    "search_engine": "brave",
    "source": "search_운송지연_항만적체",
    "search_keyword": "supply chain disruption logistics",
    "theme": "운송지연_항만적체",
    "crawled_at": "2026-06-26T09:10:07.067817"
  },
  {
    "title": "서울 지하철 대용량 리튬배터리 반입 금지 | 서울Pn",
    "url": "https://go.seoul.co.kr/news/newsView.php?id=20260626019001",
    "snippet": "서울교통공사는 지하철 화재를 막기 위해 7월 1일부터 160Wh를 초과하는 리튬배터리와 전동킥보드·전기자전거 등 배터리 구동 PM의 역사 반입을 금지했다. 지난해 합정역 배터리 연기 사고를 계기로 안전 대책을 강화했다.",
    "date": "15 hours ago",
    "search_engine": "brave",
    "source": "search_SHE_규제_위험물",
    "search_keyword": "배터리 화재 물류 규정",
    "theme": "SHE_규제_위험물",
    "crawled_at": "2026-06-26T09:10:07.417281"
  },
  {
    "title": "7월 1일부터 160Wh 초과 대용량 리튬배터리 지하철 반입 제한 < 공공PR < 퍼블릭 핫뉴스 < 기사본문 - The PR 더피알",
    "url": "https://the-pr.co.kr/news/articleView.html?idxno=61703",
    "snippet": "더피알=윤호전 기자｜지하철을 이용할 때 평소 전동킥보드나 전기자전거를 접어서 휴대하셨던 분들은 앞으로 주의가 필요하다.서울교통공사(이하 공사)는 지하철 내 화재",
    "date": "1 day ago",
    "search_engine": "brave",
    "source": "search_SHE_규제_위험물",
    "search_keyword": "배터리 화재 물류 규정",
    "theme": "SHE_규제_위험물",
    "crawled_at": "2026-06-26T09:10:07.417289"
  },
  {
    "title": "서울지하철 내달 1일부터 '전동킥보드' 반입 못한다 - 매일경제",
    "url": "https://mk.co.kr/news/society/12083274",
    "snippet": "서울교통공사가 지하철 내 화재 위험을 줄이기 위해 오는 7월 1일부터 대용량 리튬배터리와 리튬배터리로 구동되는 개인형 이동장치(PM)의 역사·열차 내 반입을 제한한다. 공사는 여객운송약관을 개정해 7월 1일부터 ...",
    "date": "15 hours ago",
    "search_engine": "brave",
    "source": "search_SHE_규제_위험물",
    "search_keyword": "배터리 화재 물류 규정",
    "theme": "SHE_규제_위험물",
    "crawled_at": "2026-06-26T09:10:07.417291"
  },
  {
    "title": "서울 지하철, 대용량 리튬배터리 반입 제한…7월 1일부터 시행 < 서울 < 전국 < 기사본문 - 내외일보",
    "url": "https://naewoeilbo.com/news/articleView.html?idxno=2369973",
    "snippet": "[내외일보] 이수한 기자 = 서울교통공사(이하 공사)는 지하철 내 화재 위험요인을 사전에 차단하고 승객 안전을 확보하기 위해 여객운송약관을 개정하고, 오는 7월",
    "date": "1 day ago",
    "search_engine": "brave",
    "source": "search_SHE_규제_위험물",
    "search_keyword": "위험물 운송 규정 변경",
    "theme": "SHE_규제_위험물",
    "crawled_at": "2026-06-26T09:10:07.721271"
  },
  {
    "title": "[TV서울] 서울 지하철, 7월부터 대용량 리튬배터리·개인형이동장치 반입 제한",
    "url": "https://tvseoul.kr/news/article.html?no=77416",
    "snippet": "[TV서울=곽재근 기자] 오는 7월부터 서울 지하철에 대용량 리튬배터리와 리튬배터리로 작동하는 개인형 이동장치(PM) 반입이 제한된다. 서울교통공사는 지하철 내 화재 위험 요인을 사전에 차단하고 승객 안전을 확보하기 위해 ...",
    "date": "1 day ago",
    "search_engine": "brave",
    "source": "search_SHE_규제_위험물",
    "search_keyword": "위험물 운송 규정 변경",
    "theme": "SHE_규제_위험물",
    "crawled_at": "2026-06-26T09:10:07.721281"
  },
  {
    "title": "[논현광장·안병억의 유러피언 드림] 유럽의 헤어질 결심 ‘기술 독립’ - 이투데이",
    "url": "https://etoday.co.kr/news/view/2597391",
    "snippet": "美빅테크 의존 줄여 기술주권 강화AI 등 규제에서 육성으로 방향전환저성장 EU, 투자여력 마련이 관건마이크로소프트의 워드와 파워포인트(PPT), 아마",
    "date": "3 hours ago",
    "search_engine": "brave",
    "source": "search_SHE_규제_위험물",
    "search_keyword": "위험물 운송 규정 변경",
    "theme": "SHE_규제_위험물",
    "crawled_at": "2026-06-26T09:10:07.721282"
  },
  {
    "title": "서울 지하철 대용량 리튬배터리 반입 금지 | 서울Pn",
    "url": "https://go.seoul.co.kr/news/newsView.php?id=20260626019001",
    "snippet": "서울교통공사는 지하철 화재를 막기 위해 7월 1일부터 160Wh를 초과하는 리튬배터리와 전동킥보드·전기자전거 등 배터리 구동 PM의 역사 반입을 금지했다. 지난해 합정역 배터리 연기 사고를 계기로 안전 대책을 강화했다.",
    "date": "15 hours ago",
    "search_engine": "brave",
    "source": "search_SHE_규제_위험물",
    "search_keyword": "리튬배터리 보관 인허가",
    "theme": "SHE_규제_위험물",
    "crawled_at": "2026-06-26T09:10:08.230376"
  },
  {
    "title": "지하철에 전동킥보드·전기자전거 못 싣는다 … 7월부터 반입 제한 | 뉴데일리",
    "url": "https://newdaily.co.kr/site/data/html/2026/06/25/2026062500116.html",
    "snippet": "오는 7월부터 서울 지하철에 전동킥보드와 전기자전거, 전동휠 등 리튬배터리로 구동되는 개인형 이동장치(PM)를 가지고 탈 수 없게 된다. 160Wh를 초과하는 대용량 리튬배터리도 역사와 열차 안으로 반입할 수 없다.서울교...",
    "date": "1 day ago",
    "search_engine": "brave",
    "source": "search_SHE_규제_위험물",
    "search_keyword": "리튬배터리 보관 인허가",
    "theme": "SHE_규제_위험물",
    "crawled_at": "2026-06-26T09:10:08.230382"
  },
  {
    "title": "서울지하철 내달 1일부터 '전동킥보드' 반입 못한다 - 매일경제",
    "url": "https://mk.co.kr/news/society/12083274",
    "snippet": "서울교통공사가 지하철 내 화재 위험을 줄이기 위해 오는 7월 1일부터 대용량 리튬배터리와 리튬배터리로 구동되는 개인형 이동장치(PM)의 역사·열차 내 반입을 제한한다. 공사는 여객운송약관을 개정해 7월 1일부터 ...",
    "date": "15 hours ago",
    "search_engine": "brave",
    "source": "search_SHE_규제_위험물",
    "search_keyword": "리튬배터리 보관 인허가",
    "theme": "SHE_규제_위험물",
    "crawled_at": "2026-06-26T09:10:08.230384"
  },
  {
    "title": "'모기약 판매 중단?' 오해 확산…약사회 대응 나서 < 약사회 < 기사본문 - 약사공론",
    "url": "https://kpanews.co.kr/news/articleView.html?idxno=537432",
    "snippet": "오는 7월부터 살생물제품 관리체계가 바뀌는 가운데 '모기약을 더 이상 살 수 없다'는 잘못된 정보가 온라인을 중심으로 확산되고 있다.이에 대한약사회(회장 권영희)",
    "date": "17 hours ago",
    "search_engine": "brave",
    "source": "search_SHE_규제_위험물",
    "search_keyword": "위험물 취급 관리규정 강화",
    "theme": "SHE_규제_위험물",
    "crawled_at": "2026-06-26T09:10:08.584911"
  },
  {
    "title": "[축산신문] 축산물이력제, 생산 넘어 유통까지 관리 확대 필요",
    "url": "https://chuksannews.co.kr/news/article.html?no=272280",
    "snippet": "[축산신문 서동휘 기자] 일각 유통과정 물량 이동·재고 관리 허점 존재 지적 실시간 디지털 관리체계 구축…유통이력 관리 강화 최근 일부 지역 축협과 유통업체를 중심으로 한우 무단 반출과 재고 조작 의혹이 발생하면서 ...",
    "date": "1 day ago",
    "search_engine": "brave",
    "source": "search_SHE_규제_위험물",
    "search_keyword": "위험물 취급 관리규정 강화",
    "theme": "SHE_규제_위험물",
    "crawled_at": "2026-06-26T09:10:08.584918"
  },
  {
    "title": "[논현광장·안병억의 유러피언 드림] 유럽의 헤어질 결심 ‘기술 독립’ - 이투데이",
    "url": "https://etoday.co.kr/news/view/2597391",
    "snippet": "美빅테크 의존 줄여 기술주권 강화AI 등 규제에서 육성으로 방향전환저성장 EU, 투자여력 마련이 관건마이크로소프트의 워드와 파워포인트(PPT), 아마",
    "date": "3 hours ago",
    "search_engine": "brave",
    "source": "search_SHE_규제_위험물",
    "search_keyword": "위험물 취급 관리규정 강화",
    "theme": "SHE_규제_위험물",
    "crawled_at": "2026-06-26T09:10:08.584920"
  },
  {
    "title": "지주회사 체제 확산되는데 이마트는 왜 '지배구조 단순화' 선택했나 : 조직 슬림화와 경영 효율에 방점",
    "url": "https://huffingtonpost.kr/article/258230",
    "snippet": "공정거래위원회가 지주회사 체제를 국내 대기업집단의 대표적 지배구조로 평가했다. 다만 신세계그룹 등 일부 대기업집단은 중간지주회사 역할을 하던 회사를 정리하는 등 예외사례로 꼽혔다. 공정위가 25일 발표한 '2026년 ...",
    "date": "1 day ago",
    "search_engine": "brave",
    "source": "search_SHE_규제_위험물",
    "search_keyword": "물류센터 화재 안전 규제",
    "theme": "SHE_규제_위험물",
    "crawled_at": "2026-06-26T09:10:08.909995"
  },
  {
    "title": "[넥스트코리아] 버려진 것에서 가치를 찾다…‘순환 경제’가 돈이 되는 시대 - 매일일보",
    "url": "https://m-i.kr/news/articleView.html?idxno=1383806",
    "snippet": "매일일보 = 민경식 기자 | 기존 산업구조를 탈피해 자원 절약·재활용으로 지속 가능성을 추구하는 경제 모델인 ‘순환 경제’가 각광받고 있다. ESG(환경·사회·지배구조) 경영 강화 추세와 맞물려 순환 경제 모델 구축 여부가 ...",
    "date": "1 day ago",
    "search_engine": "brave",
    "source": "search_SHE_규제_위험물",
    "search_keyword": "물류센터 화재 안전 규제",
    "theme": "SHE_규제_위험물",
    "crawled_at": "2026-06-26T09:10:08.910001"
  },
  {
    "title": "호르무즈서 화물선 피격 신고…IMO \"철수작전 일시 중단\"(종합) - 파이낸셜뉴스",
    "url": "https://fnnews.com/news/202606260426268388",
    "snippet": "호르무즈서 화물선 피격 신고…IMO \"철수작전 일시 중단\"(종합) UKMTO \"오만 쪽으로 지나다 피격 의심\"…소식통 \"드론 가능성\" ▲IMO \"우리 철수계획 따른 통행 아냐…안전 명확해질 때까지 중단\" (런던=연합뉴스) 김지연 특파원 ...",
    "date": "5 hours ago",
    "search_engine": "brave",
    "source": "search_SHE_규제_위험물",
    "search_keyword": "물류센터 화재 안전 규제",
    "theme": "SHE_규제_위험물",
    "crawled_at": "2026-06-26T09:10:08.910003"
  },
  {
    "title": "만기 없는 선물 美 확산, 전통 거래소 수익성 하락 압박 | 한국경제",
    "url": "https://hankyung.com/article/202606256627i",
    "snippet": "만기 없는 선물 美 확산, 전통 거래소 수익성 하락 압박, 美 상품선물위, 칼시·코인베이스 무기한 선물 허용 고레버리지에 자동청산...위험도 높아 칼시 거래량 수주 만에 85억달러 돌파 거래소 CME 12%·Cboe 26% 주가 하락 “고위험 ...",
    "date": "1 day ago",
    "search_engine": "brave",
    "source": "search_지정학_리스크",
    "search_keyword": "미중 관세 물류 영향",
    "theme": "지정학_리스크",
    "crawled_at": "2026-06-26T09:10:09.216898"
  },
  {
    "title": "선박 호르무즈 탈출 시작됐지만…운임은 요지부동 \"3분기 지나야 안정\" - 파이낸셜뉴스",
    "url": "https://fnnews.com/news/202606260531107942",
    "snippet": "[서울=뉴시스] 미국과 이란의 종전 잠정 합의 이후 호르무즈 해협에 묶였던 선박들이 순차적으로 빠져나오고 있지만 가파르게 오른 해상운임은 단기간에 안정되기는 어려울 전망이다. 선박 통항 재개로 화물·선원 안전 우려는 ...",
    "date": "4 hours ago",
    "search_engine": "brave",
    "source": "search_지정학_리스크",
    "search_keyword": "미중 관세 물류 영향",
    "theme": "지정학_리스크",
    "crawled_at": "2026-06-26T09:10:09.216904"
  },
  {
    "title": "LG 사위 윤관 BRV 해외 SPC 법인세 90억 취소…법원 “국내 고정사업장 없다” < 재계 < 기사본문 - 파이낸셜투데이",
    "url": "https://ftoday.co.kr/news/articleView.html?idxno=361087",
    "snippet": "LG그룹 고(故) 구본무 선대회장의 맏사위인 윤관 블루런벤처스(BRV) 대표가 연관된 해외 특수목적법인(SPC)에 부과된 90억원대 법인세를 둘러싼 소송에서 법원이 BRV 측의 손을 들어줬다.서울행정법원 행정5부(이정원 부장판사)는 ...",
    "date": "13 hours ago",
    "search_engine": "brave",
    "source": "search_지정학_리스크",
    "search_keyword": "미중 관세 물류 영향",
    "theme": "지정학_리스크",
    "crawled_at": "2026-06-26T09:10:09.216906"
  },
  {
    "title": "[청년일보] 코스피, 마이크론 깜짝 호실적에 5% 급등…매수 사이드카 발동",
    "url": "https://youthdaily.co.kr/news/article.html?no=221607",
    "snippet": "【 청년일보 】 코스피가 개장 직후 5% 넘게 급등하며 매수 사이드카가 발동됐다. 미국 메모리 반도체 업체 마이크론 테크놀로지가 새벽에 발표한 '깜짝 실적'의 영향으로 풀이된다. 25일 한국거래소에 따르면 코스피200 선물 ...",
    "date": "1 day ago",
    "search_engine": "brave",
    "source": "search_지정학_리스크",
    "search_keyword": "수출 규제 반도체 배터리",
    "theme": "지정학_리스크",
    "crawled_at": "2026-06-26T09:10:09.528265"
  },
  {
    "title": "[청년일보] \"정기 세일 돌입\"…백화점업계, 여름 쇼핑객 잡기 '총력'",
    "url": "https://youthdaily.co.kr/news/article.html?no=221647",
    "snippet": "【 청년일보 】 롯데·신세계·현대백화점이 본격적인 여름 휴가철을 앞두고 대규모 정기 세일과 체험형 콘텐츠를 앞세워 고객 잡기에 나섰다. 폭염과 휴가 시즌을 겨냥한 시즌 상품 할인은 물론 팝업스토어와 문화 콘텐츠를 ...",
    "date": "1 day ago",
    "search_engine": "brave",
    "source": "search_지정학_리스크",
    "search_keyword": "수출 규제 반도체 배터리",
    "theme": "지정학_리스크",
    "crawled_at": "2026-06-26T09:10:09.528274"
  },
  {
    "title": "청년일보",
    "url": "https://youthdaily.co.kr/news/article.html?no=221649",
    "snippet": "【 청년일보 】 롯데마트·슈퍼는 만성질환 관리에 특화된 기능성 혼합잡곡 2종을 출시한다고 25일 밝혔다. 농촌진흥청 국립식량과학원이 연구·개발한 특허 배합 비율이 적용된 상품으로, 찰수수·팥·차조를 배합해 혈압 ...",
    "date": "1 day ago",
    "search_engine": "brave",
    "source": "search_지정학_리스크",
    "search_keyword": "수출 규제 반도체 배터리",
    "theme": "지정학_리스크",
    "crawled_at": "2026-06-26T09:10:09.528275"
  },
  {
    "title": "정부, 자원안보 전면 강화…공급망 위기 대응 로드맵 본격 추진",
    "url": "https://kyongbuk.co.kr/news/articleView.html?idxno=4076675",
    "snippet": "정부가 미국-이란 전쟁 발발 이후 드러난 에너지·자원 수급 취약점 보완과 핵심광물 및 소재·부품을 아우르는 산업·자원 공급망을 전주기적으로 강화하기 위한 대책 마련에 들어갔다.산업통상부는 25일 서울 무역보험공...",
    "date": "14 hours ago",
    "search_engine": "brave",
    "source": "search_지정학_리스크",
    "search_keyword": "글로벌 무역 분쟁 공급망",
    "theme": "지정학_리스크",
    "crawled_at": "2026-06-26T09:10:09.866667"
  },
  {
    "title": "미-이란 MOU 이후 호르무즈 해협 통해 원유 3500만배럴 빠져나와 - 파이낸셜뉴스",
    "url": "https://fnnews.com/news/202606250748267610",
    "snippet": "미국과 이란이 호르무즈 해협의 해상 항로 개방에 전격 합의하면서 페르시아만에 발이 묶여 있던 최소 20척의 유조선이 마침내 해협을 통과한 것으로 확인됐다.앞서 미 해군은 지난 6월 18일 이란에 대한 해상 봉쇄를 ...",
    "date": "1 day ago",
    "search_engine": "brave",
    "source": "search_지정학_리스크",
    "search_keyword": "글로벌 무역 분쟁 공급망",
    "theme": "지정학_리스크",
    "crawled_at": "2026-06-26T09:10:09.866677"
  },
  {
    "title": "[미·이란 종전] 현대차·기아, '유가·중동' 이중 부담 던다",
    "url": "https://bloter.net/news/articleView.html?idxno=666514",
    "snippet": "미·이란 간 적대 행위 중단을 위한 잠정 합의 이후 호르무즈 해협의 원유 흐름이 회복되면서 현대차·기아의 중동발 비용 부담도 완화될 가능성이 커졌다. 국제유가가 분쟁 이전 수준에 근접하면서 완성차 업계에 부담으로 ...",
    "date": "1 day ago",
    "search_engine": "brave",
    "source": "search_지정학_리스크",
    "search_keyword": "글로벌 무역 분쟁 공급망",
    "theme": "지정학_리스크",
    "crawled_at": "2026-06-26T09:10:09.866680"
  },
  {
    "title": "울산해경, 부산 대변 남동방 22해리 해상 상선과 어선 충돌 사고 발생 긴급 구조 중 (3보):正筆",
    "url": "https://jeongpil.com/2575563",
    "snippet": "부산 대변 남동방 22해리 해상 상선과 어선 충돌 사고 발생 긴급 구조 [정필=김준영 기자 kspa@jeongpil.com] 울산해양경찰서는 25일 오전 10시 10분경 대변 남",
    "date": "16 hours ago",
    "search_engine": "brave",
    "source": "search_운임_유가",
    "search_keyword": "해상운임 동향",
    "theme": "운임_유가",
    "crawled_at": "2026-06-26T09:10:10.174970"
  },
  {
    "title": "‘다잉메시지’ 무시, 예정된 자멸…다 읽힌 홍명보의 ‘복붙’ 전술 | 중앙일보",
    "url": "https://joongang.co.kr/article/25440043",
    "snippet": "\"남아프리카공화국(남아공)이 (수비에서) 내려 앉았을 때 답을 찾지 못하면 어려워질 수 있다.\" 김환 JTBC 해설위원은 지난 19일(한국시간) 열린 북중미 월드컵 조별리그 A조 2차전에서 한국축구대표팀이 멕시코에 0-1로 패배한 ...",
    "date": "4 hours ago",
    "search_engine": "brave",
    "source": "search_운임_유가",
    "search_keyword": "해상운임 동향",
    "theme": "운임_유가",
    "crawled_at": "2026-06-26T09:10:10.174977"
  },
  {
    "title": "연합뉴스TV",
    "url": "https://yonhapnewstv.co.kr/news/AKR202606260412059LM",
    "snippet": "베네수엘라 북부를 강타한 강진이 튀르키예와 아이티 대지진과 유사한 형태의 지진이라는 분석이 나왔습니다. 미국 일간 뉴욕타임스는 현지시간 25일 “이번 지진이 비교적 얕은 깊이에서 발생한 데다 충격파가 단층선을 ...",
    "date": "5 hours ago",
    "search_engine": "brave",
    "source": "search_운임_유가",
    "search_keyword": "해상운임 동향",
    "theme": "운임_유가",
    "crawled_at": "2026-06-26T09:10:10.174979"
  },
  {
    "title": "CJ대한통운, 세계은행그룹과 개발도상국 공급망 혁신 방안 논의 – CJ 뉴스룸",
    "url": "https://cjnews.cj.net/cj%EB%8C%80%ED%95%9C%ED%86%B5%EC%9A%B4-%EC%84%B8%EA%B3%84%EC%9D%80%ED%96%89%EA%B7%B8%EB%A3%B9%EA%B3%BC-%EA%B0%9C%EB%B0%9C%EB%8F%84%EC%83%81%EA%B5%AD-%EA%B3%B5%EA%B8%89%EB%A7%9D-%ED%98%81%EC%8B%A0",
    "snippet": "세계은행그룹(World Bank Group)이 개발도상국의 공급망 경쟁력 강화와 물류 연결성 향상을 위한 선진 물류 모델을 살펴보기 위해 CJ대한통운을 찾았다. CJ대한통운은 세계은행그룹과 아시아·아프리카·태평양·중남미 10여 개국 ...",
    "date": "1 day ago",
    "search_engine": "brave",
    "source": "search_운임_유가",
    "search_keyword": "항공운임 변동 물류",
    "theme": "운임_유가",
    "crawled_at": "2026-06-26T09:10:10.491212"
  },
  {
    "title": "\"급여 반납합니다\" 파라타항공 비상경영 - 매일경제",
    "url": "https://mk.co.kr/news/business/12083301",
    "snippet": "고유가 후폭풍에 돈줄말라대표 100% 직원 20% 삭감",
    "date": "15 hours ago",
    "search_engine": "brave",
    "source": "search_운임_유가",
    "search_keyword": "항공운임 변동 물류",
    "theme": "운임_유가",
    "crawled_at": "2026-06-26T09:10:10.491219"
  },
  {
    "title": "3000만 외래 관광객 유치, 최대 화두는 재원...‘출국납부금 인상’ 골든타임 놓칠라 - 이투데이",
    "url": "https://etoday.co.kr/news/view/2596981",
    "snippet": "국제 관광객 급증에도 출국납부금 수입은 급감연간 1300억원 이상의 관광기금 손실 우려“관광생태계 자생력 확보 위해 기금 현실화 시급”▲9일 인천국",
    "date": "15 hours ago",
    "search_engine": "brave",
    "source": "search_운임_유가",
    "search_keyword": "항공운임 변동 물류",
    "theme": "운임_유가",
    "crawled_at": "2026-06-26T09:10:10.491220"
  },
  {
    "title": "국내 기름값 2000원선 아래로?…7차 석유 최고가격 하향 전망 - 헤럴드경제",
    "url": "https://biz.heraldcorp.com/article/10788726",
    "snippet": "[헤럴드경제=배문숙 기자]미국과 이란의 협상 진전 이후, 국제유가가 중동 전쟁 이전 수준으로 낮아지자 정부가 석유 최고가격을 하향 조정하는 방안을 검토하고 있다. 전",
    "date": "3 hours ago",
    "search_engine": "brave",
    "source": "search_운임_유가",
    "search_keyword": "국제유가 물류비 영향",
    "theme": "운임_유가",
    "crawled_at": "2026-06-26T09:10:10.796399"
  },
  {
    "title": "전쟁 이전으로 돌아간 국제유가…석유 최고가격 하향 전망 | 세계일보",
    "url": "https://segye.com/newsView/20260626502219",
    "snippet": "국제유가가 중동 전쟁 이전 수준으로 낮아지자 정부가 서민 경제의 부담을 덜기 위해 석유 최고가격을 하향 조정하는 방안을 검토하고 있다. 애초에 고유가 충격으로부터 민생을 보호하기 위해 도입했던 석유 최고가격 제도를 ...",
    "date": "3 hours ago",
    "search_engine": "brave",
    "source": "search_운임_유가",
    "search_keyword": "국제유가 물류비 영향",
    "theme": "운임_유가",
    "crawled_at": "2026-06-26T09:10:10.796406"
  },
  {
    "title": "유가 떨어져도 속타는 트럼프 - 매일경제",
    "url": "https://www.mk.co.kr/news/world/12083287",
    "snippet": "국제유가 전쟁 이전 회복 불구美 휘발유값 여전히 고공행진선거 전 물가잡기 급한 트럼프정유사에 \"빨리 내려라\" 압박",
    "date": "15 hours ago",
    "search_engine": "brave",
    "source": "search_운임_유가",
    "search_keyword": "국제유가 물류비 영향",
    "theme": "운임_유가",
    "crawled_at": "2026-06-26T09:10:10.796409"
  }
]