[
  {
    "title": "HMM, 신입사원과 반려해변 정화활동…해양 환경보호 실천 - 이투데이",
    "url": "https://etoday.co.kr/news/view/2600306",
    "snippet": "영종도 거잠포 해변서 쓰레기 수거신입사원 참여해 해양 생태 보전 의미 되새겨폐로프 재활용 등 ESG 사회공헌 지속▲지난 3일 인천 영종도 거잠포해변",
    "date": "1 day ago",
    "search_engine": "brave",
    "source": "search_운송지연_항만적체",
    "search_keyword": "글로벌 해운 지연",
    "theme": "운송지연_항만적체",
    "crawled_at": "2026-07-06T09:02:39.939071"
  },
  {
    "title": "[해양통신] 상반기 대체연료추진선 발주 137척, 2년 연속 감소",
    "url": "https://oceanpress.co.kr/news/article.html?no=30525",
    "snippet": "대체연료추진선 발주가 2년 연속 감소를 기록했다. LPG·에탄추진선은 오히려 발주가 급증하는 등 선종과 연료별로 뚜렷한 차별화가 나타났다. 노르웨이선급(DNV)이 발표한 'Alternative Fuels Insight' 자료에 따르면 2026년 상반기 ...",
    "date": "1 day ago",
    "search_engine": "brave",
    "source": "search_운송지연_항만적체",
    "search_keyword": "글로벌 해운 지연",
    "theme": "운송지연_항만적체",
    "crawled_at": "2026-07-06T09:02:39.939084"
  },
  {
    "title": "HMM 신입사원들, 인천 영종도 반려해변서 정화 활동 - 매일경제",
    "url": "https://mk.co.kr/news/business/12090524",
    "snippet": "거잠포해변서 쓰레기 수거 2023년 반려해변 입양 후 연 2회 이상 정화활동 펼쳐 해운업 터전 중요성 되새겨",
    "date": "19 hours ago",
    "search_engine": "brave",
    "source": "search_운송지연_항만적체",
    "search_keyword": "글로벌 해운 지연",
    "theme": "운송지연_항만적체",
    "crawled_at": "2026-07-06T09:02:39.939086"
  },
  {
    "title": "악연에서 절친으로...어느 해커의 '멋진 유산' - ZDNet korea",
    "url": "https://zdnet.co.kr/view/?no=20260705214509",
    "snippet": "1990년대 미국을 뒤흔든 전설적인 해커 케빈 미트닉이 과거 자신의 해킹 범죄를 저지했던 인물에게 '포르쉐 911 카레라 4 GTS' 스포츠카를 구입할 수 있는 규모의 유산을 남긴 사실이 뒤늦게 밝혀졌다.",
    "date": "11 hours ago",
    "search_engine": "brave",
    "source": "search_운송지연_항만적체",
    "search_keyword": "항만 적체 컨테이너",
    "theme": "운송지연_항만적체",
    "crawled_at": "2026-07-06T09:02:40.268238"
  },
  {
    "title": "'전기 먹는 하마' AI 데이터센터, 물도 많이 먹는다 - ZDNet korea",
    "url": "https://zdnet.co.kr/view/?no=20260705082138",
    "snippet": "인공지능(AI) 데이터센터가 빠르게 늘어나면서 빅테크사 물 사용량이 새로운 환경 문제로 부상하고 있다. 기업들이 공개하는 데이터센터 물 사용량 수치에 발전소에서 전력을 생산하는 과정에서 소비되는 물이 대부분 제외돼 ...",
    "date": "1 day ago",
    "search_engine": "brave",
    "source": "search_운송지연_항만적체",
    "search_keyword": "항만 적체 컨테이너",
    "theme": "운송지연_항만적체",
    "crawled_at": "2026-07-06T09:02:40.268250"
  },
  {
    "title": "불매보다 강력한 로켓배송...쿠팡 결제액·이용자 ‘역대 최고’ - 이투데이",
    "url": "https://etoday.co.kr/news/view/2600333",
    "snippet": "유출 이후 고객 이탈에도 결제액 4조8337억원 회복로켓배송·와우멤버십 기반 충성 고객층 위력 확인토종 G마켓·11번가, 반사이익 없이 오히려 역성장▲",
    "date": "18 hours ago",
    "search_engine": "brave",
    "source": "search_운송지연_항만적체",
    "search_keyword": "항만 적체 컨테이너",
    "theme": "운송지연_항만적체",
    "crawled_at": "2026-07-06T09:02:40.268252"
  },
  {
    "title": "How Manufacturing Leaders Can Close the Information Gap | Modern Machine Shop",
    "url": "https://mmsonline.com/articles/how-manufacturing-leaders-can-close-the-information-gap-",
    "snippet": "Shop owners and GMs do not need more information. They need earlier signals, clearer context and a better way to connect market movement to decisions about quoting, material, capacity and capital spending.",
    "date": "3 minutes ago",
    "search_engine": "brave",
    "source": "search_운송지연_항만적체",
    "search_keyword": "supply chain disruption logistics",
    "theme": "운송지연_항만적체",
    "crawled_at": "2026-07-06T09:02:40.621311"
  },
  {
    "title": "Singapore proposes governance framework for AI agents in finance | Digital Watch Observatory",
    "url": "https://dig.watch/updates/singapore-governance-framework-ai-agents-finance",
    "snippet": "Real-time validation and auditability are central to Singapore's new agentic finance safety framework.",
    "date": "10 hours ago",
    "search_engine": "brave",
    "source": "search_운송지연_항만적체",
    "search_keyword": "supply chain disruption logistics",
    "theme": "운송지연_항만적체",
    "crawled_at": "2026-07-06T09:02:40.621325"
  },
  {
    "title": "The next financial crisis may start in your shopping cart | Ctech",
    "url": "https://calcalistech.com/ctechnews/article/sodeqt4sv",
    "snippet": "Wall Street’s fast-growing BNPL and private credit system connects everyday purchases to global capital markets, raising new concerns about hidden risks.",
    "date": "13 hours ago",
    "search_engine": "brave",
    "source": "search_운송지연_항만적체",
    "search_keyword": "supply chain disruption logistics",
    "theme": "운송지연_항만적체",
    "crawled_at": "2026-07-06T09:02:40.621354"
  },
  {
    "title": "사실상 파산 수순…정부, 자금난 겪는 중소 협력사 지원 방안 논의 [문닫는 홈플러스 파장] - 이투데이",
    "url": "https://etoday.co.kr/news/view/2600288",
    "snippet": "금융위원회, 대출 상환유예 등 긴급 유동성 지원▲서울회생법원이 홈플러스의 기업회생절차 폐지를 결정한 3일 서울 시내의 한 홈플러스 매장으로 시민",
    "date": "1 day ago",
    "search_engine": "brave",
    "source": "search_SHE_규제_위험물",
    "search_keyword": "배터리 화재 물류 규정",
    "theme": "SHE_규제_위험물",
    "crawled_at": "2026-07-06T09:02:40.939089"
  },
  {
    "title": "연합뉴스TV",
    "url": "https://yonhapnewstv.co.kr/news/AKR202607051127403WZ",
    "snippet": "올해 상반기 국내 극장가 관객 수와 매출이 지난해에 비해 큰 폭으로 늘며 회복세를 보인 것으로 나타났습니다. 오늘(5일) 영화관입장권 통합전산망(KOBIS)에 따르면 올해 상반기 한국 영화 관객은 3천736만9천여명으로 지난해 ...",
    "date": "1 day ago",
    "search_engine": "brave",
    "source": "search_SHE_규제_위험물",
    "search_keyword": "배터리 화재 물류 규정",
    "theme": "SHE_규제_위험물",
    "crawled_at": "2026-07-06T09:02:40.939103"
  },
  {
    "title": "동탄 묶자 병점·권선·남양주 들썩…규제 피한 수요 ‘풍선효과’ - 이투데이",
    "url": "https://etoday.co.kr/news/view/2600077",
    "snippet": "동탄·기흥·구리 규제지역 지정 후 인접지 호가 ↑병점·권선·남양주 등 비규제 대체지 매수세 유입“규제 피한 옆 동네, 묶이기 전 사자 심리 커져”정부",
    "date": "4 hours ago",
    "search_engine": "brave",
    "source": "search_SHE_규제_위험물",
    "search_keyword": "배터리 화재 물류 규정",
    "theme": "SHE_규제_위험물",
    "crawled_at": "2026-07-06T09:02:40.939105"
  },
  {
    "title": "원유 '공급 부족→공급 과잉' 새 국면···한국경제 셈법 복잡 - 뉴스웨이",
    "url": "https://newsway.co.kr/news/view?ud=2026070510180681959",
    "snippet": "미국과 이란의 평화협정 이후 호르무즈 해협 원유 공급이 크게 늘면서 국제유가가 70달러 초반까지 급락했다. 경기 둔화와 중국의 수입 감소가 추가 하락을 부추기고 있다. 유가 하락은 국내 물가 안정과 무역수지 개선 효과가 ...",
    "date": "1 day ago",
    "search_engine": "brave",
    "source": "search_SHE_규제_위험물",
    "search_keyword": "위험물 운송 규정 변경",
    "theme": "SHE_규제_위험물",
    "crawled_at": "2026-07-06T09:02:41.233904"
  },
  {
    "title": "동탄 묶자 병점·권선·남양주 들썩…규제 피한 수요 ‘풍선효과’ - 이투데이",
    "url": "https://etoday.co.kr/news/view/2600077",
    "snippet": "동탄·기흥·구리 규제지역 지정 후 인접지 호가 ↑병점·권선·남양주 등 비규제 대체지 매수세 유입“규제 피한 옆 동네, 묶이기 전 사자 심리 커져”정부",
    "date": "4 hours ago",
    "search_engine": "brave",
    "source": "search_SHE_규제_위험물",
    "search_keyword": "위험물 운송 규정 변경",
    "theme": "SHE_규제_위험물",
    "crawled_at": "2026-07-06T09:02:41.233917"
  },
  {
    "title": "연합뉴스TV",
    "url": "https://yonhapnewstv.co.kr/news/MYH202607051120192GJ",
    "snippet": "[앵커] 6·3 지방선거 투표용지 부족 사태로 촉발된 시위가 오늘로 한 달째를 맞았습니다. 시위 초반에 비해 규모는 많이 줄어든 상황인데요. 현장 분위기 어떤지 취재기자 연결해 알아보겠습니다. 안채린 기자!",
    "date": "1 day ago",
    "search_engine": "brave",
    "source": "search_SHE_규제_위험물",
    "search_keyword": "위험물 운송 규정 변경",
    "theme": "SHE_규제_위험물",
    "crawled_at": "2026-07-06T09:02:41.233918"
  },
  {
    "title": "당정청 “반도체 생산 거점 조기 완성·전국 확산…전력부지 인허가 지원” - 이투데이",
    "url": "https://www.etoday.co.kr/news/view/2600379",
    "snippet": "고위당정협 결과…“메가 프로젝트 ‘원팀’ 지원”“서남권 ‘제2 반도체 거점’으로…생산·정주 융합”“미래대응기금, 세부 내용은 추후 논의할 계획”▲한성숙",
    "date": "14 hours ago",
    "search_engine": "brave",
    "source": "search_SHE_규제_위험물",
    "search_keyword": "리튬배터리 보관 인허가",
    "theme": "SHE_규제_위험물",
    "crawled_at": "2026-07-06T09:02:41.536524"
  },
  {
    "title": "연합뉴스TV",
    "url": "https://yonhapnewstv.co.kr/news/AKR202607060726571fa",
    "snippet": "광주제일고등학교와의 경기 중 “스타벅스 가야지“라는 응원 구호를 외쳐 거센 비판을 받은 서울 배재고 야구부 학생들이 오늘(6일) 광주를 찾아 사과합니다. 서울시교육청과 전남광주교육청에 따르면 배재고 야구부 소속 ...",
    "date": "2 hours ago",
    "search_engine": "brave",
    "source": "search_SHE_규제_위험물",
    "search_keyword": "리튬배터리 보관 인허가",
    "theme": "SHE_규제_위험물",
    "crawled_at": "2026-07-06T09:02:41.536537"
  },
  {
    "title": "[기획] 유통 성장 공식…대형 점포보다 ‘AI·물류망·플랫폼’ 경쟁력 - 매일일보",
    "url": "https://m-i.kr/news/articleView.html?idxno=1388023",
    "snippet": "매일일보 = 강소슬 기자 | 국내 유통업계의 성장 공식이 바뀌고 있다. 과거에는 좋은 입지와 대형 점포, 상품 구색이 경쟁력의 핵심이었다면 최근에는 인공지능(AI), 물류망, 플랫폼 경쟁력이 실적을 좌우하는 주요 변수로 ...",
    "date": "1 day ago",
    "search_engine": "brave",
    "source": "search_SHE_규제_위험물",
    "search_keyword": "리튬배터리 보관 인허가",
    "theme": "SHE_규제_위험물",
    "crawled_at": "2026-07-06T09:02:41.536539"
  },
  {
    "title": "고물가가 바꾼 유통 단계...정부는 온라인도매 키우고, 이커머스 ‘산지직송’ 구슬땀 - 이투데이",
    "url": "https://etoday.co.kr/news/view/2595689",
    "snippet": "농식품부·aT, 온라인도매시장 열어 유통 구조 디지털 전환쿠팡·컬리·농협, 독자 물류망 기반 산지 직거래로 유통비 최대 20% 절감지역 중소업체 매출·",
    "date": "3 hours ago",
    "search_engine": "brave",
    "source": "search_SHE_규제_위험물",
    "search_keyword": "위험물 취급 관리규정 강화",
    "theme": "SHE_규제_위험물",
    "crawled_at": "2026-07-06T09:02:41.851571"
  },
  {
    "title": "中 거리두는 韓반도체, 소부장 공급망 재편 - 전자신문",
    "url": "https://etnews.com/20260703000213",
    "snippet": "삼성전자와 SK하이닉스가 중국 의존도가 높은 반도체 소재·부품·장비(소부장) 공급망 재편에 나섰다. 미국의 대중국 규제 강화 가능성에 선제 대응하기 위해 일부 중국산 장비를 한국과 미국 등 다른 국가 제품으로 대체하는 ...",
    "date": "16 hours ago",
    "search_engine": "brave",
    "source": "search_SHE_규제_위험물",
    "search_keyword": "위험물 취급 관리규정 강화",
    "theme": "SHE_규제_위험물",
    "crawled_at": "2026-07-06T09:02:41.851580"
  },
  {
    "title": "HBM 호황에 가려진 중국의 추격…D램 기술 격차 3년 수준 [중국 반도체 굴기 2026 上] - 이투데이",
    "url": "https://etoday.co.kr/news/view/2600181",
    "snippet": "중국 D램, 기술·생산 모두 빠른 추격CXMT, IPO 발판으로 투자 확대HBM은 한국 우위…장기 추격 변수AI 슈퍼사이클에 힘입어 국내 반도체 업계는 사상",
    "date": "4 hours ago",
    "search_engine": "brave",
    "source": "search_SHE_규제_위험물",
    "search_keyword": "위험물 취급 관리규정 강화",
    "theme": "SHE_규제_위험물",
    "crawled_at": "2026-07-06T09:02:41.851581"
  },
  {
    "title": "동탄 묶자 병점·권선·남양주 들썩…규제 피한 수요 ‘풍선효과’ - 이투데이",
    "url": "https://etoday.co.kr/news/view/2600077",
    "snippet": "동탄·기흥·구리 규제지역 지정 후 인접지 호가 ↑병점·권선·남양주 등 비규제 대체지 매수세 유입“규제 피한 옆 동네, 묶이기 전 사자 심리 커져”정부",
    "date": "4 hours ago",
    "search_engine": "brave",
    "source": "search_SHE_규제_위험물",
    "search_keyword": "물류센터 화재 안전 규제",
    "theme": "SHE_규제_위험물",
    "crawled_at": "2026-07-06T09:02:42.138198"
  },
  {
    "title": "고물가가 바꾼 유통 단계...정부는 온라인도매 키우고, 이커머스 ‘산지직송’ 구슬땀 - 이투데이",
    "url": "https://etoday.co.kr/news/view/2595689",
    "snippet": "농식품부·aT, 온라인도매시장 열어 유통 구조 디지털 전환쿠팡·컬리·농협, 독자 물류망 기반 산지 직거래로 유통비 최대 20% 절감지역 중소업체 매출·",
    "date": "3 hours ago",
    "search_engine": "brave",
    "source": "search_SHE_규제_위험물",
    "search_keyword": "물류센터 화재 안전 규제",
    "theme": "SHE_규제_위험물",
    "crawled_at": "2026-07-06T09:02:42.138209"
  },
  {
    "title": "\"택배차 싹 다 바꾼다\"... 최대 할인 480만 원 할인에, 실구매가 2천만 원대 진입? < 업계소식 < 뉴스 < 기사본문 - 오토트리뷴",
    "url": "https://autotribune.co.kr/news/articleView.html?idxno=44068",
    "snippet": "[오토트리뷴=양봉수 기자] 배송 현장에서 전기 상용차를 고를 때 가장 먼저 묻는 말은 \"얼마나 빨리 충전되냐\"다. 현대차 전기밴 ST1은 이 질문에 20분이라는",
    "date": "19 hours ago",
    "search_engine": "brave",
    "source": "search_SHE_규제_위험물",
    "search_keyword": "물류센터 화재 안전 규제",
    "theme": "SHE_규제_위험물",
    "crawled_at": "2026-07-06T09:02:42.138211"
  },
  {
    "title": "트럼프 감세법 1년…환급 늘었지만 적자·복지 그늘",
    "url": "https://edaily.co.kr/News/Read?mediaCodeNo=257&newsId=01643286645511568",
    "snippet": "도널드 트럼프 미국 대통령의 대표 감세법 ‘하나의 크고 아름다운 법안’(OBBBA·One Big Beautiful Bill Act)이 시행 1년을 맞이한 가운데, 세금 환급은 늘었지만 정부 재정적자가 불어나고 저소득층 복지는 약화했다는 평가가 ...",
    "date": "19 hours ago",
    "search_engine": "brave",
    "source": "search_지정학_리스크",
    "search_keyword": "미중 관세 물류 영향",
    "theme": "지정학_리스크",
    "crawled_at": "2026-07-06T09:02:42.500094"
  },
  {
    "title": "[기획] ‘점원’보다 ‘물류 인재’…유통 고용축 바뀐다 - 매일일보",
    "url": "https://m-i.kr/news/articleView.html?idxno=1388027",
    "snippet": "매일일보 = 강소슬 기자 | 유통업 고용의 무게중심이 물류·배송 직군으로 옮겨가고 있다. 과거 유통업 일자리는 백화점, 대형마트, 편의점 등 매장에서 고객을 응대하고 상품을 판매하는 인력이 중심이었지만, 지금은 온라인 ...",
    "date": "1 day ago",
    "search_engine": "brave",
    "source": "search_지정학_리스크",
    "search_keyword": "미중 관세 물류 영향",
    "theme": "지정학_리스크",
    "crawled_at": "2026-07-06T09:02:42.500107"
  },
  {
    "title": "호르무즈서 발 빼는 유럽…오만은 美·이란 사이 '아슬아슬 줄타기'",
    "url": "https://edaily.co.kr/News/Read?mediaCodeNo=257&newsId=01354646645511568",
    "snippet": "미국과 이란의 휴전으로 호르무즈 해협의 긴장이 누그러지자 프랑스가 약 두 달간 인근 해역에 배치했던 유일한 항공모함 샤를드골함을 본국으로 불러들이기로 했다.프랑스 항공모함 샤를드골함이 지난 4월 27일 ...",
    "date": "1 day ago",
    "search_engine": "brave",
    "source": "search_지정학_리스크",
    "search_keyword": "미중 관세 물류 영향",
    "theme": "지정학_리스크",
    "crawled_at": "2026-07-06T09:02:42.500109"
  },
  {
    "title": "인니 원자재 수출 규제 파장... 韓 전력·식품 가격 오르나 - 파이낸셜뉴스",
    "url": "https://www.fnnews.com/news/202607050742562659",
    "snippet": "인도네시아가 석탄과 팜유, 페로니켈 등 3대 핵심 원자재의 수출을 국영기업이 직접 관리·감독하는 체제로 전환하기로 하면서 글로벌 원자재 공급망에 큰 변화가 예상된다.인도네시아의 이번 조치는 중국을 비롯한 주요 ...",
    "date": "3 hours ago",
    "search_engine": "brave",
    "source": "search_지정학_리스크",
    "search_keyword": "수출 규제 반도체 배터리",
    "theme": "지정학_리스크",
    "crawled_at": "2026-07-06T09:02:42.790876"
  },
  {
    "title": "中 거리두는 韓반도체, 소부장 공급망 재편 - 전자신문",
    "url": "https://etnews.com/20260703000213",
    "snippet": "삼성전자와 SK하이닉스가 중국 의존도가 높은 반도체 소재·부품·장비(소부장) 공급망 재편에 나섰다. 미국의 대중국 규제 강화 가능성에 선제 대응하기 위해 일부 중국산 장비를 한국과 미국 등 다른 국가 제품으로 대체하는 ...",
    "date": "16 hours ago",
    "search_engine": "brave",
    "source": "search_지정학_리스크",
    "search_keyword": "수출 규제 반도체 배터리",
    "theme": "지정학_리스크",
    "crawled_at": "2026-07-06T09:02:42.790887"
  },
  {
    "title": "[사설] '반도체 소부장 주권' 더 높여가야 - 전자신문",
    "url": "https://etnews.com/20260705000050",
    "snippet": "본지 취재를 종합하면 메모리 반도체 글로벌 패권을 쥔 삼성전자, SK하이닉스 두 회사가 중국 의존도를 높게 유지해왔던 소재·부품·장비(소부장) 공급망에 중대한 변화를 주기 시작한 것으로 파악됐다.",
    "date": "15 hours ago",
    "search_engine": "brave",
    "source": "search_지정학_리스크",
    "search_keyword": "수출 규제 반도체 배터리",
    "theme": "지정학_리스크",
    "crawled_at": "2026-07-06T09:02:42.790889"
  },
  {
    "title": "中 거리두는 韓반도체, 소부장 공급망 재편 - 전자신문",
    "url": "https://etnews.com/20260703000213",
    "snippet": "삼성전자와 SK하이닉스가 중국 의존도가 높은 반도체 소재·부품·장비(소부장) 공급망 재편에 나섰다. 미국의 대중국 규제 강화 가능성에 선제 대응하기 위해 일부 중국산 장비를 한국과 미국 등 다른 국가 제품으로 대체하는 ...",
    "date": "16 hours ago",
    "search_engine": "brave",
    "source": "search_지정학_리스크",
    "search_keyword": "글로벌 무역 분쟁 공급망",
    "theme": "지정학_리스크",
    "crawled_at": "2026-07-06T09:02:43.111570"
  },
  {
    "title": "美·EU·英 이어 日까지 … 높아지는 철강 보호무역 - 매일경제",
    "url": "https://mk.co.kr/news/business/12090643",
    "snippet": "韓 일본에 협력 손 내밀었지만日, 한국산 반덤핑 조사나서업계 \"전기료 등 지원 절실해\"",
    "date": "16 hours ago",
    "search_engine": "brave",
    "source": "search_지정학_리스크",
    "search_keyword": "글로벌 무역 분쟁 공급망",
    "theme": "지정학_리스크",
    "crawled_at": "2026-07-06T09:02:43.111584"
  },
  {
    "title": "트럼프에 무역·외교 핵심까지…美정부와 넓고 깊게 엮인 쿠팡 | 연합뉴스",
    "url": "https://yna.co.kr/view/AKR20260705024100071",
    "snippet": "(워싱턴=연합뉴스) 조준형 특파원 = 최근 공개된 도널드 트럼프 미국 대통령의 재산 신고 내역에서 트럼프 대통령이 투자계좌 운용사를 통해 쿠팡 ...",
    "date": "20 hours ago",
    "search_engine": "brave",
    "source": "search_지정학_리스크",
    "search_keyword": "글로벌 무역 분쟁 공급망",
    "theme": "지정학_리스크",
    "crawled_at": "2026-07-06T09:02:43.111586"
  },
  {
    "title": "공장엔 LS전선, 배엔 대한전선...해저케이블에 국책금융 6300억 붙었다",
    "url": "https://insight.co.kr/news/561479",
    "snippet": "LS전선과 대한전선의 해저케이블 생산·시공 인프라에 올해 확인된 국책금융 지원 규모가 6300억원까지 늘었다.",
    "date": "3 hours ago",
    "search_engine": "brave",
    "source": "search_운임_유가",
    "search_keyword": "해상운임 동향",
    "theme": "운임_유가",
    "crawled_at": "2026-07-06T09:02:43.402042"
  },
  {
    "title": "황령산 나무들의 통곡...부산의 중심에서 무슨 일 벌어지고 있나 - 오마이뉴스",
    "url": "https://ohmynews.com/NWS_Web/Series/series_premium_pg.aspx?BLCK_NO=1&CMPT_CD=T0016&CNTN_CD=A0003246559&PAGE_CD=ET001",
    "snippet": "부산 황령산에서 2조2천억원 규모의 케이블카·전망타워·호텔 개발 사업이 추진되고 있다. 황령산지키기범시민운동본부는 식물 399종, 곤충 153종이 서식하는 생태계를 지키기 위해 반대 운동을 펼치고 있다.",
    "date": "2 hours ago",
    "search_engine": "brave",
    "source": "search_운임_유가",
    "search_keyword": "해상운임 동향",
    "theme": "운임_유가",
    "crawled_at": "2026-07-06T09:02:43.402053"
  },
  {
    "title": "설탕 줄이고 맛은 살리고…‘건강한 단맛’ 식품시장 공략 [강원대 앵커사업단] - 매일경제",
    "url": "https://mk.co.kr/news/society/12090138",
    "snippet": "스마트 시티 구현을 위한 핵심 기술 동향은?",
    "date": "9 hours ago",
    "search_engine": "brave",
    "source": "search_운임_유가",
    "search_keyword": "해상운임 동향",
    "theme": "운임_유가",
    "crawled_at": "2026-07-06T09:02:43.402054"
  },
  {
    "title": "[2026 재계 인물 탐구 ㉔] 이상윤 티웨이항공 대표, 중·장거리 노선·화물 사업·소노그룹 지원에 ‘훨훨’ < 기획 < 기사본문 - 이코노미트리뷴",
    "url": "https://economytribune.co.kr/news/articleView.html?idxno=3903249",
    "snippet": "2026년은 국내외 변화와 혁신의 파고가 그 어느 때보다 높고 거셀 전망이다. 도널드 트럼프 미국 행정부가 펼치는 관세 전쟁은 좀처럼 출구를 찾지 못한 채 현재진",
    "date": "19 hours ago",
    "search_engine": "brave",
    "source": "search_운임_유가",
    "search_keyword": "항공운임 변동 물류",
    "theme": "운임_유가",
    "crawled_at": "2026-07-06T09:02:43.677233"
  },
  {
    "title": "동탄 묶자 병점·권선·남양주 들썩…규제 피한 수요 ‘풍선효과’ - 이투데이",
    "url": "https://etoday.co.kr/news/view/2600077",
    "snippet": "동탄·기흥·구리 규제지역 지정 후 인접지 호가 ↑병점·권선·남양주 등 비규제 대체지 매수세 유입“규제 피한 옆 동네, 묶이기 전 사자 심리 커져”정부",
    "date": "4 hours ago",
    "search_engine": "brave",
    "source": "search_운임_유가",
    "search_keyword": "항공운임 변동 물류",
    "theme": "운임_유가",
    "crawled_at": "2026-07-06T09:02:43.677245"
  },
  {
    "title": "[기획] 유통 성장 공식…대형 점포보다 ‘AI·물류망·플랫폼’ 경쟁력 - 매일일보",
    "url": "https://m-i.kr/news/articleView.html?idxno=1388023",
    "snippet": "매일일보 = 강소슬 기자 | 국내 유통업계의 성장 공식이 바뀌고 있다. 과거에는 좋은 입지와 대형 점포, 상품 구색이 경쟁력의 핵심이었다면 최근에는 인공지능(AI), 물류망, 플랫폼 경쟁력이 실적을 좌우하는 주요 변수로 ...",
    "date": "1 day ago",
    "search_engine": "brave",
    "source": "search_운임_유가",
    "search_keyword": "항공운임 변동 물류",
    "theme": "운임_유가",
    "crawled_at": "2026-07-06T09:02:43.677246"
  },
  {
    "title": "원유 '공급 부족→공급 과잉' 새 국면···한국경제 셈법 복잡 - 뉴스웨이",
    "url": "https://newsway.co.kr/news/view?ud=2026070510180681959",
    "snippet": "미국과 이란의 평화협정 이후 호르무즈 해협 원유 공급이 크게 늘면서 국제유가가 70달러 초반까지 급락했다. 경기 둔화와 중국의 수입 감소가 추가 하락을 부추기고 있다. 유가 하락은 국내 물가 안정과 무역수지 개선 효과가 ...",
    "date": "1 day ago",
    "search_engine": "brave",
    "source": "search_운임_유가",
    "search_keyword": "국제유가 물류비 영향",
    "theme": "운임_유가",
    "crawled_at": "2026-07-06T09:02:43.976548"
  },
  {
    "title": "주유소 기름값 7주째 하락 - 매일경제",
    "url": "https://www.mk.co.kr/news/business/12090729",
    "snippet": "주유소 기름값 7주째 하락 국제유가 하락의 영향으로 국내 주유소 휘발유·경유 가격이 1900원대 중반으로 하락했다.한국석유공사에 따르면 7월 첫째 주(6월 28일~7월 2일) 전국 주유소 휘발유 평균 판매가는 지난주보다 리터당 ...",
    "date": "15 hours ago",
    "search_engine": "brave",
    "source": "search_운임_유가",
    "search_keyword": "국제유가 물류비 영향",
    "theme": "운임_유가",
    "crawled_at": "2026-07-06T09:02:43.976561"
  },
  {
    "title": "불매보다 강력한 로켓배송...쿠팡 결제액·이용자 ‘역대 최고’ - 이투데이",
    "url": "https://etoday.co.kr/news/view/2600333",
    "snippet": "유출 이후 고객 이탈에도 결제액 4조8337억원 회복로켓배송·와우멤버십 기반 충성 고객층 위력 확인토종 G마켓·11번가, 반사이익 없이 오히려 역성장▲",
    "date": "18 hours ago",
    "search_engine": "brave",
    "source": "search_운임_유가",
    "search_keyword": "국제유가 물류비 영향",
    "theme": "운임_유가",
    "crawled_at": "2026-07-06T09:02:43.976563"
  }
]